dxf2x/__init__.py
dxf2x/compiler.py
dxf2x/dxf.py
dxf2x/model_pb2.py
dxf2x/proto.py
dxf2x/svg.py
dxf2x/tsv.py
dxf2x-0.0.1.dist-info/LICENSE
dxf2x-0.0.1.dist-info/METADATA
dxf2x-0.0.1.dist-info/WHEEL
dxf2x-0.0.1.dist-info/entry_points.txt
dxf2x-0.0.1.dist-info/top_level.txt
dxf2x-0.0.1.dist-info/RECORD
