Metadata-Version: 2.1
Name: dxf2x
Version: 0.0.1
Summary: Convert between DXF, TSV, SVG, PXF(Protobuf) formats.
Home-page: http://github.com/redraiment/dxf2x
Author: redraiment
Author-email: redraiment@gmail.com
License: UNKNOWN
Platform: UNKNOWN
Requires-Python: >=3.7
